tzdata/__init__.py
tzdata/zones
tzdata/zoneinfo/CET
tzdata/zoneinfo/CST6CDT
tzdata/zoneinfo/Cuba
tzdata/zoneinfo/EET
tzdata/zoneinfo/EST
tzdata/zoneinfo/EST5EDT
tzdata/zoneinfo/Egypt
tzdata/zoneinfo/Eire
tzdata/zoneinfo/Factory
tzdata/zoneinfo/GB
tzdata/zoneinfo/GB-Eire
tzdata/zoneinfo/GMT
tzdata/zoneinfo/GMT+0
tzdata/zoneinfo/GMT-0
tzdata/zoneinfo/GMT0
tzdata/zoneinfo/Greenwich
tzdata/zoneinfo/HST
tzdata/zoneinfo/Hongkong
tzdata/zoneinfo/Iceland
tzdata/zoneinfo/Iran
tzdata/zoneinfo/Israel
tzdata/zoneinfo/Jamaica
tzdata/zoneinfo/Japan
tzdata/zoneinfo/Kwajalein
tzdata/zoneinfo/Libya
tzdata/zoneinfo/MET
tzdata/zoneinfo/MST
tzdata/zoneinfo/MST7MDT
tzdata/zoneinfo/NZ
tzdata/zoneinfo/NZ-CHAT
tzdata/zoneinfo/Navajo
tzdata/zoneinfo/PRC
tzdata/zoneinfo/PST8PDT
tzdata/zoneinfo/Poland
tzdata/zoneinfo/Portugal
tzdata/zoneinfo/ROC
tzdata/zoneinfo/ROK
tzdata/zoneinfo/Singapore
tzdata/zoneinfo/Turkey
tzdata/zoneinfo/UCT
tzdata/zoneinfo/UTC
tzdata/zoneinfo/Universal
tzdata/zoneinfo/W-SU
tzdata/zoneinfo/WET
tzdata/zoneinfo/Zulu
tzdata/zoneinfo/__init__.py
tzdata/zoneinfo/iso3166.tab
tzdata/zoneinfo/leapseconds
tzdata/zoneinfo/tzdata.zi
tzdata/zoneinfo/zone.tab
tzdata/zoneinfo/zone1970.tab
tzdata/zoneinfo/Africa/Abidjan
tzdata/zoneinfo/Africa/Accra
tzdata/zoneinfo/Africa/Addis_Ababa
tzdata/zoneinfo/Africa/Algiers
tzdata/zoneinfo/Africa/Asmara
tzdata/zoneinfo/Africa/Asmera
tzdata/zoneinfo/Africa/Bamako
tzdata/zoneinfo/Africa/Bangui
tzdata/zoneinfo/Africa/Banjul
tzdata/zoneinfo/Africa/Bissau
tzdata/zoneinfo/Africa/Blantyre
tzdata/zoneinfo/Africa/Brazzaville
tzdata/zoneinfo/Africa/Bujumbura
tzdata/zoneinfo/Africa/Cairo
tzdata/zoneinfo/Africa/Casablanca
tzdata/zoneinfo/Africa/Ceuta
tzdata/zoneinfo/Africa/Conakry
tzdata/zoneinfo/Africa/Dakar
tzdata/zoneinfo/Africa/Dar_es_Salaam
tzdata/zoneinfo/Africa/Djibouti
tzdata/zoneinfo/Africa/Douala
tzdata/zoneinfo/Africa/El_Aaiun
tzdata/zoneinfo/Africa/Freetown
tzdata/zoneinfo/Africa/Gaborone
tzdata/zoneinfo/Africa/Harare
tzdata-2021.3.dist-info/LICENSE
tzdata-2021.3.dist-info/LICENSE_APACHE
tzdata-2021.3.dist-info/METADATA
tzdata-2021.3.dist-info/WHEEL
tzdata-2021.3.dist-info/top_level.txt
tzdata-2021.3.dist-info/RECORD
