Metadata-Version: 2.1
Name: tzdata
Version: 2021.3
Summary: Provider of IANA time zone data
Home-page: https://github.com/python/tzdata
Author: Python Software Foundation
Author-email: datetime-sig@python.org
License: Apache-2.0
Project-URL: Bug Reports, https://github.com/python/tzdata/issues
Project-URL: Source, https://github.com/python/tzdata
Project-URL: Documentation, https://tzdata.readthedocs.io
Platform: UNKNOWN
Classifier: Development Status :: 4 - Beta
Classifier: Intended Audience :: Developers
Classifier: License :: OSI Approved :: Apache Software License
Classifier: Programming Language :: Python :: 2
Classifier: Programming Language :: Python :: 3
Requires-Python: >=2
License-File: LICENSE
License-File: licenses/LICENSE_APACHE
